Metadata-Version: 2.1
Name: check-device-code
Version: 1.0.1
Summary: 校验手机设备码
Home-page: https://github.com/Cuile/check_device_code
Author: cuile
Author-email: i@cuile.com
License: UNKNOWN
Keywords: imei emid
Platform: UNKNOWN
